MANIFEST.in
README.rst
setup.py
fh_drf_common.egg-info/PKG-INFO
fh_drf_common.egg-info/SOURCES.txt
fh_drf_common.egg-info/dependency_links.txt
fh_drf_common.egg-info/requires.txt
fh_drf_common.egg-info/top_level.txt
rest_framework_common/__init__.py
rest_framework_common/filters.py
rest_framework_common/mixins.py
rest_framework_common/pagination.py
rest_framework_common/permissions.py
rest_framework_common/serializers.py
rest_framework_common/test.py
rest_framework_common/throttling.py
rest_framework_common/validators.py