Metadata-Version: 1.0
Name: fh-drf-common
Version: 0.1.14
Summary: A library to provide common functionality for Django Rest Framework projects.
Home-page: https://gitlab.com/futurehaus/drf-common
Author: UNKNOWN
Author-email: UNKNOWN
License: UNKNOWN
Platform: UNKNOWN
